LICENSE.txt
MANIFEST.in
README.txt
VERSION.txt
server.py
setup.py
docs/Makefile
docs/conf.py
docs/index.rst
docs/make.bat
eventfd/__init__.py
eventfd/_eventfd.c
eventfd/_eventfd.py
eventfd.egg-info/PKG-INFO
eventfd.egg-info/SOURCES.txt
eventfd.egg-info/dependency_links.txt
eventfd.egg-info/top_level.txt
test/test_eventfd.py