Metadata-Version: 1.0
Name: eventfd
Version: 0.2
Summary: threading.Event like class that has a file descriptor and can be used in select/poll
Home-page: http://eventfd.readthedocs.org
Author: Aviv Palivoda
Author-email: palaviv@gmail.com
License: Simplified BSD License
Platform: UNKNOWN
